[
  {
    "id": 1,
    "armyId": 1,
    "name": "步兵1",
    "makePrice": 100,
    "makeOil": 0,
    "level": 1,
    "makeLimit": 9999,
    "atk": 100,
    "def": 200,
    "spd": 10,
    "pace": 1,
    "minRange": 1,
    "maxRange": 1,
    "instantFire": 1,
    "atkType": 1,
    "defType": 1,
    "unlockPrice": 1000,
    "unlockOil": 0,
    "prevId": 0,
    "nextId": 2
  },
  {
    "id": 2,
    "armyId": 1,
    "name": "步兵2",
    "makePrice": 100,
    "makeOil": 0,
    "level": 2,
    "makeLimit": 9999,
    "atk": 102,
    "def": 204,
    "spd": 10,
    "pace": 1,
    "minRange": 1,
    "maxRange": 1,
    "instantFire": 1,
    "atkType": 1,
    "defType": 1,
    "unlockPrice": 2000,
    "unlockOil": 0,
    "prevId": 1,
    "nextId": 3
  },
  {
    "id": 3,
    "armyId": 1,
    "name": "步兵3",
    "makePrice": 100,
    "makeOil": 0,
    "level": 3,
    "makeLimit": 9999,
    "atk": 104,
    "def": 208,
    "spd": 10,
    "pace": 1,
    "minRange": 1,
    "maxRange": 1,
    "instantFire": 1,
    "atkType": 1,
    "defType": 1,
    "unlockPrice": 3000,
    "unlockOil": 0,
    "prevId": 2,
    "nextId": 4
  },
  {
    "id": 4,
    "armyId": 1,
    "name": "步兵4",
    "makePrice": 100,
    "makeOil": 0,
    "level": 4,
    "makeLimit": 9999,
    "atk": 106,
    "def": 212,
    "spd": 10,
    "pace": 1,
    "minRange": 1,
    "maxRange": 1,
    "instantFire": 1,
    "atkType": 1,
    "defType": 1,
    "unlockPrice": 4000,
    "unlockOil": 0,
    "prevId": 3,
    "nextId": 5
  },
  {
    "id": 5,
    "armyId": 1,
    "name": "步兵5",
    "makePrice": 100,
    "makeOil": 0,
    "level": 5,
    "makeLimit": 9999,
    "atk": 108,
    "def": 216,
    "spd": 10,
    "pace": 1,
    "minRange": 1,
    "maxRange": 1,
    "instantFire": 1,
    "atkType": 1,
    "defType": 1,
    "unlockPrice": 5000,
    "unlockOil": 0,
    "prevId": 4,
    "nextId": 6
  },
  {
    "id": 6,
    "armyId": 1,
    "name": "步兵6",
    "makePrice": 100,
    "makeOil": 0,
    "level": 6,
    "makeLimit": 9999,
    "atk": 110,
    "def": 220,
    "spd": 10,
    "pace": 1,
    "minRange": 1,
    "maxRange": 1,
    "instantFire": 1,
    "atkType": 1,
    "defType": 1,
    "unlockPrice": 6000,
    "unlockOil": 0,
    "prevId": 5,
    "nextId": 7
  },
  {
    "id": 7,
    "armyId": 1,
    "name": "步兵7",
    "makePrice": 100,
    "makeOil": 0,
    "level": 7,
    "makeLimit": 9999,
    "atk": 112,
    "def": 224,
    "spd": 10,
    "pace": 1,
    "minRange": 1,
    "maxRange": 1,
    "instantFire": 1,
    "atkType": 1,
    "defType": 1,
    "unlockPrice": 7000,
    "unlockOil": 0,
    "prevId": 6,
    "nextId": 8
  },
  {
    "id": 8,
    "armyId": 1,
    "name": "步兵8",
    "makePrice": 100,
    "makeOil": 0,
    "level": 8,
    "makeLimit": 9999,
    "atk": 114,
    "def": 228,
    "spd": 10,
    "pace": 1,
    "minRange": 1,
    "maxRange": 1,
    "instantFire": 1,
    "atkType": 1,
    "defType": 1,
    "unlockPrice": 8000,
    "unlockOil": 0,
    "prevId": 7,
    "nextId": 9
  },
  {
    "id": 9,
    "armyId": 1,
    "name": "步兵9",
    "makePrice": 100,
    "makeOil": 0,
    "level": 9,
    "makeLimit": 9999,
    "atk": 116,
    "def": 232,
    "spd": 10,
    "pace": 1,
    "minRange": 1,
    "maxRange": 1,
    "instantFire": 1,
    "atkType": 1,
    "defType": 1,
    "unlockPrice": 9000,
    "unlockOil": 0,
    "prevId": 8,
    "nextId": 10
  },
  {
    "id": 10,
    "armyId": 1,
    "name": "步兵10",
    "makePrice": 100,
    "makeOil": 0,
    "level": 10,
    "makeLimit": 9999,
    "atk": 118,
    "def": 236,
    "spd": 10,
    "pace": 1,
    "minRange": 1,
    "maxRange": 1,
    "instantFire": 1,
    "atkType": 1,
    "defType": 1,
    "unlockPrice": 10000,
    "unlockOil": 0,
    "prevId": 9,
    "nextId": 0
  },
  {
    "id": 11,
    "armyId": 2,
    "name": "大炮1",
    "makePrice": 1000,
    "makeOil": 0,
    "level": 1,
    "makeLimit": 9999,
    "atk": 200,
    "def": 50,
    "spd": 3,
    "pace": 1,
    "minRange": 2,
    "maxRange": 3,
    "instantFire": 0,
    "atkType": 2,
    "defType": 2,
    "unlockPrice": 11000,
    "unlockOil": 0,
    "prevId": 0,
    "nextId": 12
  },
  {
    "id": 12,
    "armyId": 2,
    "name": "大炮2",
    "makePrice": 1000,
    "makeOil": 0,
    "level": 2,
    "makeLimit": 9999,
    "atk": 202,
    "def": 54,
    "spd": 3,
    "pace": 1,
    "minRange": 2,
    "maxRange": 3,
    "instantFire": 0,
    "atkType": 2,
    "defType": 2,
    "unlockPrice": 12000,
    "unlockOil": 0,
    "prevId": 11,
    "nextId": 13
  },
  {
    "id": 13,
    "armyId": 2,
    "name": "大炮3",
    "makePrice": 1000,
    "makeOil": 0,
    "level": 3,
    "makeLimit": 9999,
    "atk": 204,
    "def": 58,
    "spd": 3,
    "pace": 1,
    "minRange": 2,
    "maxRange": 3,
    "instantFire": 0,
    "atkType": 2,
    "defType": 2,
    "unlockPrice": 13000,
    "unlockOil": 0,
    "prevId": 12,
    "nextId": 14
  },
  {
    "id": 14,
    "armyId": 2,
    "name": "大炮4",
    "makePrice": 1000,
    "makeOil": 0,
    "level": 4,
    "makeLimit": 9999,
    "atk": 206,
    "def": 62,
    "spd": 3,
    "pace": 1,
    "minRange": 2,
    "maxRange": 3,
    "instantFire": 0,
    "atkType": 2,
    "defType": 2,
    "unlockPrice": 14000,
    "unlockOil": 0,
    "prevId": 13,
    "nextId": 15
  },
  {
    "id": 15,
    "armyId": 2,
    "name": "大炮5",
    "makePrice": 1000,
    "makeOil": 0,
    "level": 5,
    "makeLimit": 9999,
    "atk": 208,
    "def": 66,
    "spd": 3,
    "pace": 1,
    "minRange": 2,
    "maxRange": 3,
    "instantFire": 0,
    "atkType": 2,
    "defType": 2,
    "unlockPrice": 15000,
    "unlockOil": 0,
    "prevId": 14,
    "nextId": 16
  },
  {
    "id": 16,
    "armyId": 2,
    "name": "大炮6",
    "makePrice": 1000,
    "makeOil": 0,
    "level": 6,
    "makeLimit": 9999,
    "atk": 210,
    "def": 70,
    "spd": 3,
    "pace": 1,
    "minRange": 2,
    "maxRange": 3,
    "instantFire": 0,
    "atkType": 2,
    "defType": 2,
    "unlockPrice": 16000,
    "unlockOil": 0,
    "prevId": 15,
    "nextId": 17
  },
  {
    "id": 17,
    "armyId": 2,
    "name": "大炮7",
    "makePrice": 1000,
    "makeOil": 0,
    "level": 7,
    "makeLimit": 9999,
    "atk": 212,
    "def": 74,
    "spd": 3,
    "pace": 1,
    "minRange": 2,
    "maxRange": 3,
    "instantFire": 0,
    "atkType": 2,
    "defType": 2,
    "unlockPrice": 17000,
    "unlockOil": 0,
    "prevId": 16,
    "nextId": 18
  },
  {
    "id": 18,
    "armyId": 2,
    "name": "大炮8",
    "makePrice": 1000,
    "makeOil": 0,
    "level": 8,
    "makeLimit": 9999,
    "atk": 214,
    "def": 78,
    "spd": 3,
    "pace": 1,
    "minRange": 2,
    "maxRange": 3,
    "instantFire": 0,
    "atkType": 2,
    "defType": 2,
    "unlockPrice": 18000,
    "unlockOil": 0,
    "prevId": 17,
    "nextId": 19
  },
  {
    "id": 19,
    "armyId": 2,
    "name": "大炮9",
    "makePrice": 1000,
    "makeOil": 0,
    "level": 9,
    "makeLimit": 9999,
    "atk": 216,
    "def": 82,
    "spd": 3,
    "pace": 1,
    "minRange": 2,
    "maxRange": 3,
    "instantFire": 0,
    "atkType": 2,
    "defType": 2,
    "unlockPrice": 19000,
    "unlockOil": 0,
    "prevId": 18,
    "nextId": 20
  },
  {
    "id": 20,
    "armyId": 2,
    "name": "大炮10",
    "makePrice": 1000,
    "makeOil": 0,
    "level": 10,
    "makeLimit": 9999,
    "atk": 218,
    "def": 86,
    "spd": 3,
    "pace": 1,
    "minRange": 2,
    "maxRange": 3,
    "instantFire": 0,
    "atkType": 2,
    "defType": 2,
    "unlockPrice": 20000,
    "unlockOil": 0,
    "prevId": 19,
    "nextId": 0
  },
  {
    "id": 21,
    "armyId": 3,
    "name": "坦克1",
    "makePrice": 3000,
    "makeOil": 0,
    "level": 1,
    "makeLimit": 9999,
    "atk": 180,
    "def": 300,
    "spd": 20,
    "pace": 2,
    "minRange": 1,
    "maxRange": 2,
    "instantFire": 1,
    "atkType": 3,
    "defType": 3,
    "unlockPrice": 21000,
    "unlockOil": 0,
    "prevId": 0,
    "nextId": 22
  },
  {
    "id": 22,
    "armyId": 3,
    "name": "坦克2",
    "makePrice": 3000,
    "makeOil": 0,
    "level": 2,
    "makeLimit": 9999,
    "atk": 182,
    "def": 304,
    "spd": 20,
    "pace": 2,
    "minRange": 1,
    "maxRange": 2,
    "instantFire": 1,
    "atkType": 3,
    "defType": 3,
    "unlockPrice": 22000,
    "unlockOil": 0,
    "prevId": 21,
    "nextId": 23
  },
  {
    "id": 23,
    "armyId": 3,
    "name": "坦克3",
    "makePrice": 3000,
    "makeOil": 0,
    "level": 3,
    "makeLimit": 9999,
    "atk": 184,
    "def": 308,
    "spd": 20,
    "pace": 2,
    "minRange": 1,
    "maxRange": 2,
    "instantFire": 1,
    "atkType": 3,
    "defType": 3,
    "unlockPrice": 23000,
    "unlockOil": 0,
    "prevId": 22,
    "nextId": 24
  },
  {
    "id": 24,
    "armyId": 3,
    "name": "坦克4",
    "makePrice": 3000,
    "makeOil": 0,
    "level": 4,
    "makeLimit": 9999,
    "atk": 186,
    "def": 312,
    "spd": 20,
    "pace": 2,
    "minRange": 1,
    "maxRange": 2,
    "instantFire": 1,
    "atkType": 3,
    "defType": 3,
    "unlockPrice": 24000,
    "unlockOil": 0,
    "prevId": 23,
    "nextId": 25
  },
  {
    "id": 25,
    "armyId": 3,
    "name": "坦克5",
    "makePrice": 3000,
    "makeOil": 0,
    "level": 5,
    "makeLimit": 9999,
    "atk": 188,
    "def": 316,
    "spd": 20,
    "pace": 2,
    "minRange": 1,
    "maxRange": 2,
    "instantFire": 1,
    "atkType": 3,
    "defType": 3,
    "unlockPrice": 25000,
    "unlockOil": 0,
    "prevId": 24,
    "nextId": 26
  },
  {
    "id": 26,
    "armyId": 3,
    "name": "坦克6",
    "makePrice": 3000,
    "makeOil": 0,
    "level": 6,
    "makeLimit": 9999,
    "atk": 190,
    "def": 320,
    "spd": 20,
    "pace": 2,
    "minRange": 1,
    "maxRange": 2,
    "instantFire": 1,
    "atkType": 3,
    "defType": 3,
    "unlockPrice": 26000,
    "unlockOil": 0,
    "prevId": 25,
    "nextId": 27
  },
  {
    "id": 27,
    "armyId": 3,
    "name": "坦克7",
    "makePrice": 3000,
    "makeOil": 0,
    "level": 7,
    "makeLimit": 9999,
    "atk": 192,
    "def": 324,
    "spd": 20,
    "pace": 2,
    "minRange": 1,
    "maxRange": 2,
    "instantFire": 1,
    "atkType": 3,
    "defType": 3,
    "unlockPrice": 27000,
    "unlockOil": 0,
    "prevId": 26,
    "nextId": 28
  },
  {
    "id": 28,
    "armyId": 3,
    "name": "坦克8",
    "makePrice": 3000,
    "makeOil": 0,
    "level": 8,
    "makeLimit": 9999,
    "atk": 194,
    "def": 328,
    "spd": 20,
    "pace": 2,
    "minRange": 1,
    "maxRange": 2,
    "instantFire": 1,
    "atkType": 3,
    "defType": 3,
    "unlockPrice": 28000,
    "unlockOil": 0,
    "prevId": 27,
    "nextId": 29
  },
  {
    "id": 29,
    "armyId": 3,
    "name": "坦克9",
    "makePrice": 3000,
    "makeOil": 0,
    "level": 9,
    "makeLimit": 9999,
    "atk": 196,
    "def": 332,
    "spd": 20,
    "pace": 2,
    "minRange": 1,
    "maxRange": 2,
    "instantFire": 1,
    "atkType": 3,
    "defType": 3,
    "unlockPrice": 29000,
    "unlockOil": 0,
    "prevId": 28,
    "nextId": 30
  },
  {
    "id": 30,
    "armyId": 3,
    "name": "坦克10",
    "makePrice": 3000,
    "makeOil": 0,
    "level": 10,
    "makeLimit": 9999,
    "atk": 198,
    "def": 336,
    "spd": 20,
    "pace": 2,
    "minRange": 1,
    "maxRange": 2,
    "instantFire": 1,
    "atkType": 3,
    "defType": 3,
    "unlockPrice": 30000,
    "unlockOil": 0,
    "prevId": 29,
    "nextId": 0
  },
  {
    "id": 31,
    "armyId": 4,
    "name": "战斗机1",
    "makePrice": 20000,
    "makeOil": 0,
    "level": 1,
    "makeLimit": 9999,
    "atk": 100,
    "def": 100,
    "spd": 200,
    "pace": 4,
    "minRange": 1,
    "maxRange": 2,
    "instantFire": 1,
    "atkType": 4,
    "defType": 4,
    "unlockPrice": 50000,
    "unlockOil": 0,
    "prevId": 0,
    "nextId": 32
  },
  {
    "id": 32,
    "armyId": 4,
    "name": "战斗机2",
    "makePrice": 20000,
    "makeOil": 0,
    "level": 2,
    "makeLimit": 9999,
    "atk": 102,
    "def": 104,
    "spd": 200,
    "pace": 4,
    "minRange": 1,
    "maxRange": 2,
    "instantFire": 1,
    "atkType": 4,
    "defType": 4,
    "unlockPrice": 60000,
    "unlockOil": 0,
    "prevId": 31,
    "nextId": 33
  },
  {
    "id": 33,
    "armyId": 4,
    "name": "战斗机3",
    "makePrice": 20000,
    "makeOil": 0,
    "level": 3,
    "makeLimit": 9999,
    "atk": 104,
    "def": 108,
    "spd": 200,
    "pace": 4,
    "minRange": 1,
    "maxRange": 2,
    "instantFire": 1,
    "atkType": 4,
    "defType": 4,
    "unlockPrice": 70000,
    "unlockOil": 0,
    "prevId": 32,
    "nextId": 34
  },
  {
    "id": 34,
    "armyId": 4,
    "name": "战斗机4",
    "makePrice": 20000,
    "makeOil": 0,
    "level": 4,
    "makeLimit": 9999,
    "atk": 106,
    "def": 112,
    "spd": 200,
    "pace": 4,
    "minRange": 1,
    "maxRange": 2,
    "instantFire": 1,
    "atkType": 4,
    "defType": 4,
    "unlockPrice": 80000,
    "unlockOil": 0,
    "prevId": 33,
    "nextId": 35
  },
  {
    "id": 35,
    "armyId": 4,
    "name": "战斗机5",
    "makePrice": 20000,
    "makeOil": 0,
    "level": 5,
    "makeLimit": 9999,
    "atk": 108,
    "def": 116,
    "spd": 200,
    "pace": 4,
    "minRange": 1,
    "maxRange": 2,
    "instantFire": 1,
    "atkType": 4,
    "defType": 4,
    "unlockPrice": 90000,
    "unlockOil": 0,
    "prevId": 34,
    "nextId": 36
  },
  {
    "id": 36,
    "armyId": 4,
    "name": "战斗机6",
    "makePrice": 20000,
    "makeOil": 0,
    "level": 6,
    "makeLimit": 9999,
    "atk": 110,
    "def": 120,
    "spd": 200,
    "pace": 4,
    "minRange": 1,
    "maxRange": 2,
    "instantFire": 1,
    "atkType": 4,
    "defType": 4,
    "unlockPrice": 100000,
    "unlockOil": 0,
    "prevId": 35,
    "nextId": 37
  },
  {
    "id": 37,
    "armyId": 4,
    "name": "战斗机7",
    "makePrice": 20000,
    "makeOil": 0,
    "level": 7,
    "makeLimit": 9999,
    "atk": 112,
    "def": 124,
    "spd": 200,
    "pace": 4,
    "minRange": 1,
    "maxRange": 2,
    "instantFire": 1,
    "atkType": 4,
    "defType": 4,
    "unlockPrice": 110000,
    "unlockOil": 0,
    "prevId": 36,
    "nextId": 38
  },
  {
    "id": 38,
    "armyId": 4,
    "name": "战斗机8",
    "makePrice": 20000,
    "makeOil": 0,
    "level": 8,
    "makeLimit": 9999,
    "atk": 114,
    "def": 128,
    "spd": 200,
    "pace": 4,
    "minRange": 1,
    "maxRange": 2,
    "instantFire": 1,
    "atkType": 4,
    "defType": 4,
    "unlockPrice": 120000,
    "unlockOil": 0,
    "prevId": 37,
    "nextId": 39
  },
  {
    "id": 39,
    "armyId": 4,
    "name": "战斗机9",
    "makePrice": 20000,
    "makeOil": 0,
    "level": 9,
    "makeLimit": 9999,
    "atk": 116,
    "def": 132,
    "spd": 200,
    "pace": 4,
    "minRange": 1,
    "maxRange": 2,
    "instantFire": 1,
    "atkType": 4,
    "defType": 4,
    "unlockPrice": 130000,
    "unlockOil": 0,
    "prevId": 38,
    "nextId": 40
  },
  {
    "id": 40,
    "armyId": 4,
    "name": "战斗机10",
    "makePrice": 20000,
    "makeOil": 0,
    "level": 10,
    "makeLimit": 9999,
    "atk": 118,
    "def": 136,
    "spd": 200,
    "pace": 4,
    "minRange": 1,
    "maxRange": 2,
    "instantFire": 1,
    "atkType": 4,
    "defType": 4,
    "unlockPrice": 140000,
    "unlockOil": 0,
    "prevId": 39,
    "nextId": 0
  },
  {
    "id": 41,
    "armyId": 5,
    "name": "轰炸机1",
    "makePrice": 40000,
    "makeOil": 0,
    "level": 1,
    "makeLimit": 9999,
    "atk": 300,
    "def": 100,
    "spd": 120,
    "pace": 3,
    "minRange": 1,
    "maxRange": 2,
    "instantFire": 0,
    "atkType": 5,
    "defType": 4,
    "unlockPrice": 80000,
    "unlockOil": 0,
    "prevId": 0,
    "nextId": 42
  },
  {
    "id": 42,
    "armyId": 5,
    "name": "轰炸机2",
    "makePrice": 40000,
    "makeOil": 0,
    "level": 2,
    "makeLimit": 9999,
    "atk": 302,
    "def": 104,
    "spd": 120,
    "pace": 3,
    "minRange": 1,
    "maxRange": 2,
    "instantFire": 0,
    "atkType": 5,
    "defType": 4,
    "unlockPrice": 100000,
    "unlockOil": 0,
    "prevId": 41,
    "nextId": 43
  },
  {
    "id": 43,
    "armyId": 5,
    "name": "轰炸机3",
    "makePrice": 40000,
    "makeOil": 0,
    "level": 3,
    "makeLimit": 9999,
    "atk": 304,
    "def": 108,
    "spd": 120,
    "pace": 3,
    "minRange": 1,
    "maxRange": 2,
    "instantFire": 0,
    "atkType": 5,
    "defType": 4,
    "unlockPrice": 120000,
    "unlockOil": 0,
    "prevId": 42,
    "nextId": 44
  },
  {
    "id": 44,
    "armyId": 5,
    "name": "轰炸机4",
    "makePrice": 40000,
    "makeOil": 0,
    "level": 4,
    "makeLimit": 9999,
    "atk": 306,
    "def": 112,
    "spd": 120,
    "pace": 3,
    "minRange": 1,
    "maxRange": 2,
    "instantFire": 0,
    "atkType": 5,
    "defType": 4,
    "unlockPrice": 140000,
    "unlockOil": 0,
    "prevId": 43,
    "nextId": 45
  },
  {
    "id": 45,
    "armyId": 5,
    "name": "轰炸机5",
    "makePrice": 40000,
    "makeOil": 0,
    "level": 5,
    "makeLimit": 9999,
    "atk": 308,
    "def": 116,
    "spd": 120,
    "pace": 3,
    "minRange": 1,
    "maxRange": 2,
    "instantFire": 0,
    "atkType": 5,
    "defType": 4,
    "unlockPrice": 160000,
    "unlockOil": 0,
    "prevId": 44,
    "nextId": 46
  },
  {
    "id": 46,
    "armyId": 5,
    "name": "轰炸机6",
    "makePrice": 40000,
    "makeOil": 0,
    "level": 6,
    "makeLimit": 9999,
    "atk": 310,
    "def": 120,
    "spd": 120,
    "pace": 3,
    "minRange": 1,
    "maxRange": 2,
    "instantFire": 0,
    "atkType": 5,
    "defType": 4,
    "unlockPrice": 180000,
    "unlockOil": 0,
    "prevId": 45,
    "nextId": 47
  },
  {
    "id": 47,
    "armyId": 5,
    "name": "轰炸机7",
    "makePrice": 40000,
    "makeOil": 0,
    "level": 7,
    "makeLimit": 9999,
    "atk": 312,
    "def": 124,
    "spd": 120,
    "pace": 3,
    "minRange": 1,
    "maxRange": 2,
    "instantFire": 0,
    "atkType": 5,
    "defType": 4,
    "unlockPrice": 200000,
    "unlockOil": 0,
    "prevId": 46,
    "nextId": 48
  },
  {
    "id": 48,
    "armyId": 5,
    "name": "轰炸机8",
    "makePrice": 40000,
    "makeOil": 0,
    "level": 8,
    "makeLimit": 9999,
    "atk": 314,
    "def": 128,
    "spd": 120,
    "pace": 3,
    "minRange": 1,
    "maxRange": 2,
    "instantFire": 0,
    "atkType": 5,
    "defType": 4,
    "unlockPrice": 220000,
    "unlockOil": 0,
    "prevId": 47,
    "nextId": 49
  },
  {
    "id": 49,
    "armyId": 5,
    "name": "轰炸机9",
    "makePrice": 40000,
    "makeOil": 0,
    "level": 9,
    "makeLimit": 9999,
    "atk": 316,
    "def": 132,
    "spd": 120,
    "pace": 3,
    "minRange": 1,
    "maxRange": 2,
    "instantFire": 0,
    "atkType": 5,
    "defType": 4,
    "unlockPrice": 240000,
    "unlockOil": 0,
    "prevId": 48,
    "nextId": 50
  },
  {
    "id": 50,
    "armyId": 5,
    "name": "轰炸机10",
    "makePrice": 40000,
    "makeOil": 0,
    "level": 10,
    "makeLimit": 9999,
    "atk": 318,
    "def": 136,
    "spd": 120,
    "pace": 3,
    "minRange": 1,
    "maxRange": 2,
    "instantFire": 0,
    "atkType": 5,
    "defType": 4,
    "unlockPrice": 260000,
    "unlockOil": 0,
    "prevId": 49,
    "nextId": 0
  }
]